gan_v3.v
module gan_v3 #(parameter WIDTH=32)
(
    input wire clk,
    input wire rst,
    input wire signed [WIDTH-1:0] data_in,
    input wire [7:0] addr,
    input wire we,
    input wire start,

    // output
    output reg signed [WIDTH-1:0] data_out,

    output reg data_valid
);

   

    // memori 1 neuron
    reg signed [WIDTH-1:0] X1, X2, X3, X4;
    reg signed [WIDTH-1:0] Y [0:3];
    reg signed [WIDTH-1:0] W1, W2, W3, W4;
    reg signed [WIDTH-1:0] B;

    reg signed [WIDTH-1:0] mult_result [0:3];

    reg [2:0] y_key;
    reg [4:0] neuron_key;

    reg [2:0] output_key;


    reg signed [WIDTH-1:0] temp, temp_add1, temp_add2;

    // input\
     parameter n_x = 4;
    parameter n_w = 54;
    parameter n_b = 19;
    
    reg signed [WIDTH-1:0] x [0: n_x-1];

    reg signed [WIDTH-1:0] w [0: n_w-1];

    reg signed [WIDTH-1:0] b [0: n_b-1];

    // data input register

    reg done_loading;

    reg [3:0] STATE;
    parameter LOAD_DATA = 4'b0001, ASSIGN   = 4'b0010,
              MULTIPLY = 4'b0011, ADD_1      = 4'b0111, ADD_2      = 4'b1000,
                ADD_BIAS = 4'b0100, RELU       = 4'b0101, FINISH     = 4'b0110;


    always @(posedge clk ) begin

    if (rst) begin
        X1 <= 0; X2 <= 0; X3 <= 0; X4 <= 0;
        Y[0] <= 0; Y[1] <= 0; Y[2] <= 0; Y[3] <= 0;
        W1 <= 0; W2 <= 0; W3 <= 0; W4 <= 0;
        B <= 0;
        done_loading <= 1'b0;

        STATE <= LOAD_DATA;

    end // if rst

    else begin

        case (STATE)

            LOAD_DATA : begin

                if (we) begin

                    if (addr < n_x) begin
                        x[addr] <= data_in;
                    end // if x

                    else if (addr < n_x + n_w) begin
                        w[addr - n_x] <= data_in;
                    end // if w

                    else if (addr < n_x + n_w + n_b ) begin
                        b[addr - n_x - n_w] <= data_in;
                    end // if b

                    if (addr == n_x + n_w + n_b - 1) begin
                        STATE <= ASSIGN;
                        done_loading <= 1'b1;
                        neuron_key <= 0;
                    end

                end // if we

            end // LOAD_DATA

            ASSIGN : begin

                case (neuron_key) 
                // layer 1
                    0: begin
                        X1 <= x[0];
                        X2 <= x[1];
                        X3 <= x[2];
                        X4 <= x[3];

                        W1 <= w[0];
                        W2 <= w[1];
                        W3 <= w[2];
                        W4 <= w[3];

                        B  <= b[0];

                        y_key <= 0;
                        
                        neuron_key <= neuron_key + 1;
                    end //0

                    1: begin

                        W1 <= w[4];
                        W2 <= w[5];
                        W3 <= w[6];
                        W4 <= w[7];

                        B  <= b[1];

                        y_key <= 1;

                        neuron_key <= neuron_key + 1;
                    end //1

                    2: begin

                        W1 <= w[8];
                        W2 <= w[9];
                        W3 <= w[10];
                        W4 <= w[11];

                        B  <= b[2];

                        y_key <= 2;

                        neuron_key <= neuron_key + 1;
                    end //2

                    3: begin

                        W1 <= w[12];
                        W2 <= w[13];
                        W3 <= w[14];
                        W4 <= w[15];

                        B  <= b[3];

                        y_key <= 3;

                        STATE <= MULTIPLY;

                        neuron_key <= neuron_key + 1;

                    end //3

                    // layer 2
                    4 : begin 
                        X1 <= Y[0];
                        X2 <= Y[1];
                        X3 <= Y[2];
                        X4 <= Y[3];
                        W1 <= w[16];
                        W2 <= w[17];
                        W3 <= w[18];
                        W4 <= w[19];
                        B  <= b[4];
                        y_key <= 0;

                        neuron_key <= neuron_key + 1;
                        
                    end //4

                    5 : begin 
                        W1 <= w[20];
                        W2 <= w[21];
                        W3 <= w[22];
                        W4 <= w[23];

                        B  <= b[5];

                        y_key <= 1;
                        
                        neuron_key <= neuron_key + 1;

                    end //5

                    // layer 3
                    6 : begin
                        X1 <= Y[0];
                        X2 <= Y[1];
                        X3 <= 0;
                        X4 <= 0;
                        W1 <= w[24];
                        W2 <= w[25];
                        W3 <= 0;
                        W4 <= 0;
                        B  <= b[6];
                        y_key <= 0;

                        neuron_key <= neuron_key + 1;
                        
                    end //6

                    // layer 4
                    7 : begin
                        X1 <= Y[0];
                        X2 <= 0;
                        X3 <= 0;
                        X4 <= 0;
                        W1 <= w[26];
                        W2 <= 0;
                        W3 <= 0;
                        W4 <= 0;
                        B  <= b[7];
                        y_key <= 0;

                        neuron_key <= neuron_key + 1;
                        
                    end //7
                    // layer 5
                    8 : begin
                        X1 <= Y[0];
                        X2 <= 0;
                        X3 <= 0;
                        X4 <= 0;
                        W1 <= w[27];
                        W2 <= 0;
                        W3 <= 0;
                        W4 <= 0;
                        B  <= b[8];
                        y_key <= 0;

                        neuron_key <= neuron_key + 1;
                        
                    end //8

                    // layer 6
                    9 : begin
                        X1 <= Y[0];
                        X2 <= 0;
                        X3 <= 0;
                        X4 <= 0;
                        W1 <= w[28];
                        W2 <= 0;
                        W3 <= 0;
                        W4 <= 0;
                        B  <= b[9];
                        y_key <= 0;

                        neuron_key <= neuron_key + 1;
                        
                    end //9

                    10 : begin
                        W1 <= w[29];
                        W2 <= 0;
                        W3 <= 0;
                        W4 <= 0;
                        B  <= b[10];
                        y_key <= 1;

                        neuron_key <= neuron_key + 1;
                        
                    end //10

                    // layer 7
                    11 : begin
                        X1 <= Y[0];
                        X2 <= Y[1];
                        X3 <= 0;
                        X4 <= 0;
                        W1 <= w[30];
                        W2 <= w[31];
                        W3 <= 0;
                        W4 <= 0;
                        B  <= b[11];
                        y_key <= 0;

                        neuron_key <= neuron_key + 1;
                        
                    end //11

                    12 : begin
                        W1 <= w[32];
                        W2 <= w[33];
                        W3 <= 0;
                        W4 <= 0;
                        B  <= b[12];
                        y_key <= 1;

                        neuron_key <= neuron_key + 1;
                        
                    end //12

                    13 : begin
                        W1 <= w[34];
                        W2 <= w[35];
                        W3 <= 0;
                        W4 <= 0;
                        B  <= b[13];
                        y_key <= 2;

                        neuron_key <= neuron_key + 1;
                        
                    end //13

                    14 : begin
                        W1 <= w[36];
                        W2 <= w[37];
                        W3 <= 0;
                        W4 <= 0;
                        B  <= b[14];
                        y_key <= 3;

                        neuron_key <= neuron_key + 1;
                        
                    end //14

                    // layer 8

                    15 : begin
                        X1 <= Y[0];
                        X2 <= Y[1];
                        X3 <= Y[2];
                        X4 <= Y[3];

                        W1 <= w[38];
                        W2 <= w[39];
                        W3 <= w[40];
                        W4 <= w[41];

                        B  <= b[15];

                        y_key <= 0;

                        neuron_key <= neuron_key + 1;
                    end //15

                    16 : begin

                        W1 <= w[42];
                        W2 <= w[43];
                        W3 <= w[44];
                        W4 <= w[45];

                        B  <= b[16];

                        y_key <= 1;

                        neuron_key <= neuron_key + 1;
                    end //16

                    17 : begin

                        W1 <= w[46];
                        W2 <= w[47];
                        W3 <= w[48];
                        W4 <= w[49];

                        B  <= b[17];

                        y_key <= 2;

                        neuron_key <= neuron_key + 1;
                    end //17

                    18 : begin

                        W1 <= w[50];
                        W2 <= w[51];
                        W3 <= w[52];
                        W4 <= w[53];

                        B  <= b[18];

                        y_key <= 3;

                        neuron_key <= neuron_key + 1;
                    end //18


                    default: ;
                    


                endcase // neuron_key
                STATE <= MULTIPLY;
                end // ASSIGN

            MULTIPLY : begin

                mult_result[0] <= X1*W1;
                mult_result[1] <= X2*W2;
                mult_result[2] <= X3*W3;
                mult_result[3] <= X4*W4;

                STATE <= ADD_1;

            end // MULTIPLY


            ADD_1 : begin
                temp_add1 <= mult_result[0] + mult_result[1];
                temp_add2 <= mult_result[2] + mult_result[3];
                STATE <= ADD_2;
            end // ADD_1

            ADD_2 : begin
                Y[y_key] <= temp_add1 + temp_add2;
                STATE <= ADD_BIAS;
            end // ADD_2

            ADD_BIAS : begin

                Y[y_key] <= Y[y_key] + B;
                STATE <= RELU;

            end // ADD

            RELU : begin
                temp = Y[y_key];
                if (temp < 0)
                    Y[y_key] <= 0;
                else
                    Y[y_key] <= temp;

                if (neuron_key < 19) begin
                    STATE <= ASSIGN;
                end else begin
                    STATE <= FINISH;
                    output_key <= 0;
                end

            end // ADD

           
            FINISH : begin
                case (output_key)
                    0: begin
                        data_out <= Y[0];
                        output_key <= output_key + 1;
                    end
                    1: begin
                        data_out <= Y[1];
                        output_key <= output_key + 1;
                    end
                    2: begin
                        data_out <= Y[2];
                        output_key <= output_key + 1;
                    end
                    3: begin
                        data_out <= Y[3];
                        output_key <= output_key + 1;
                        data_valid <= 1'b1;
                    end
                    default: ;
                endcase // output_key
            end // FINISH



            default: ;
        endcase // state    

    end // else rst
    end // always posedge clk or rst

    
endmodule

tb_gan_v3.v
`timescale 1ns/1ps
module tb_gan_v3;

    parameter WIDTH = 28;

    reg clk;
    reg rst;
    reg we;
    reg start;
    reg signed [WIDTH-1:0] data_in;
    reg [7:0] addr;
    wire signed [WIDTH-1:0] data_out;
    wire data_valid;

    // DUT (Device Under Test)
    gan_v3 #(WIDTH) uut (
        .clk(clk),
        .rst(rst),
        .data_in(data_in),
        .addr(addr),
        .we(we),
        .start(start),
        .data_out(data_out),

        .data_valid(data_valid)
    );

    // clock generator
    always #5 clk = ~clk;

    integer i;

    parameter n_x = 4;
    parameter n_w = 54;
    parameter n_b = 19;

    reg signed [WIDTH-1:0] x_in [0:n_x-1];
    reg signed [WIDTH-1:0] w_in [0:n_w-1];
    reg signed [WIDTH-1:0] b_in [0:n_b-1];


    

    // reg signed [WIDTH-1:0] y_out [0:3];
    reg signed [WIDTH-1:0] y_out [0:3];



    initial begin

    $dumpfile("wave.vcd");  // nama file untuk GTKWave
    $dumpvars(0, tb_gan_v3); // rekam semua sinyal dalam testbench

    x_in[0] = 32'sd0;
    x_in[1] = 32'sd1;
    x_in[2] = 32'sd1;
    x_in[3] = 32'sd0;

    w_in[0]  = 32'sd6; // w11
    w_in[1]  = -32'sd3; // w21
    w_in[2]  = 32'sd5; // w31
    w_in[3]  = -32'sd16; // w41

    w_in[4]  = 32'sd21; // w12
    w_in[5]  = 32'sd16; // w22
    w_in[6]  = -32'sd6; // w32
    w_in[7]  = -32'sd9; // w42

    w_in[8]  = 32'sd3;  // w13
    w_in[9]  = -32'sd3; // w23
    w_in[10] = -32'sd15; // w33
    w_in[11] = -32'sd17; // w43

    w_in[12] = 32'sd18; // w14
    w_in[13] = 32'sd12; // w24
    w_in[14] = -32'sd4; // w34
    w_in[15] = -32'sd8; // w44

    b_in[0] = 32'sd1;
    b_in[1] = 32'sd0;
    b_in[2] = 32'sd2;
    b_in[3] = -32'sd1;

    w_in[16] = 32'sd4; // w11
    w_in[17] = 32'sd14; // w21
    w_in[18] = 32'sd8;  // w31
    w_in[19] = 32'sd15; // w41

    w_in[20] = -32'sd14; // w12
    w_in[21] = 32'sd14;  // w22
    w_in[22] = 32'sd9;   // w32
    w_in[23] = 32'sd15;  // w42

    b_in[4] = 32'sd1; // b14
    b_in[5] = 32'sd4; // b24

    w_in[24] = 32'sd14; // w11
    w_in[25] = 32'sd6;  // w21

    b_in[6] = 32'sd5;

    w_in[26] = 32'sd7; // w11
    b_in[7] = 32'sd10;

    w_in[27] = 32'sd1; // w11
    b_in[8] = -32'sd4;

    w_in[28] = -32'sd8; // w11
    w_in[29] = 32'sd14; // w12
    b_in[9] = 32'sd20;
    b_in[10] = 32'sd0;

    w_in[30] = 32'sd4; //w11
    w_in[31] = -32'sd14; // w21

    w_in[32] = 32'sd14; // w12
    w_in[33] = 32'sd14; // w22

    w_in[34] = 32'sd8; // w13
    w_in[35] = 32'sd9; // w23

    w_in[36] = 32'sd15; // w14
    w_in[37] = 32'sd15; // w24

    b_in[11] = 32'sd5;
    b_in[12] = 32'sd3;
    b_in[13] = 32'sd1;
    b_in[14] = 32'sd2;
   // layer 8
    w_in[38] = 32'sd11; // w11
    w_in[39] = 32'sd9;  // w21
    w_in[40] = 32'sd10; // w31
    w_in[41] = 32'sd1;  // w41

    w_in[42] = -32'sd7; // w12
    w_in[43] = -32'sd6; // w22
    w_in[44] = -32'sd15; // w32
    w_in[45] = 32'sd17; // w42

    w_in[46] = 32'sd10; // w13
    w_in[47] = 32'sd11; // w23
    w_in[48] = -32'sd5; // w33
    w_in[49] = 32'sd4;  // w43

    w_in[50] = -32'sd7; // w14
    w_in[51] = -32'sd7; // w24
    w_in[52] = 32'sd7;  // w34
    w_in[53] = 32'sd12; // w44

    b_in[15] = -32'sd10;
    b_in[16] = 32'sd10;
    b_in[17] = 32'sd10;
    b_in[18] = -32'sd10;

    clk = 0;
    rst = 1;
        we  = 0;
        start = 0;
        addr = 0;
        data_in = 0;

        #10 rst = 0;

        // mulai loading data
        we = 1;
        for (i = 0; i < 4; i = i + 1) begin  // 4 (x) + 16 (w) + 4 (b)
            @(posedge clk);
            addr <= i;  
            data_in <= x_in[i];  // isi dengan nilai 0,1,2,...23
        end

        for (i = 0; i < 54; i = i + 1) begin  // 4 (x) + 16 (w) + 4 (b)
            @(posedge clk);
            addr <= i + 4;  
            data_in <= w_in[i];  // isi dengan nilai 0,1,2,...23
        end

        for (i = 0; i < 19; i = i + 1) begin  // 4 (x) + 16 (w) + 4 (b)
            @(posedge clk);
            addr <= i + 58;  
            data_in <= b_in[i];  // isi dengan nilai 0,1,2,...23
        end
        repeat(2) @(posedge clk);

        we = 0;

        // tunggu sebentar

        // print isi register x, w, b
        // $display("\n=== ISI REGISTER X ===");
        // for (i = 0; i < uut.n_x; i = i + 1)
        //     $display("x[%0d] = %0d", i, uut.x[i]);

        // $display("\n=== ISI REGISTER W ===");
        // for (i = 0; i < uut.n_w; i = i + 1)
        //     $display("w[%0d] = %0d", i, uut.w[i]);

        // $display("\n=== ISI REGISTER B ===");
        // for (i = 0; i < uut.n_b; i = i + 1)
        //     $display("b[%0d] = %0d", i, uut.b[i]);

        // $display ("\n nilai addr: %0d", addr);
        $display("== GAN LEVEL 3 : Hardware Sharing ==");

        $display("\n nilai done_loading: %b", uut.done_loading);
        
        $display("\n=== TEST SELESAI ===");

        repeat(114) @(posedge clk);
        $display("neuron_key = %0d", uut.neuron_key);


        @(posedge clk);
        $display("data_out1 = %0d", uut.data_out);
        @(posedge clk);
        $display("data_out2 = %0d", uut.data_out);
        @(posedge clk);
        $display("data_out3 = %0d", uut.data_out);
        @(posedge clk);
        $display("data_out4 = %0d", uut.data_out);



        $stop;
        $finish;
    end


    
endmodule

wave.vcd
$date
	Fri Nov 14 09:20:52 2025
$end
$version
	Icarus Verilog
$end
$timescale
	1ps
$end
$scope module tb_gan_v3 $end
$var wire 1 ! data_valid $end
$var wire 28 " data_out [27:0] $end
$var parameter 32 # WIDTH $end
$var parameter 32 $ n_b $end
$var parameter 32 % n_w $end
$var parameter 32 & n_x $end
$var reg 8 ' addr [7:0] $end
$var reg 1 ( clk $end
$var reg 28 ) data_in [27:0] $end
$var reg 1 * rst $end
$var reg 1 + start $end
$var reg 1 , we $end
$var integer 32 - i [31:0] $end
$scope module uut $end
$var wire 8 . addr [7:0] $end
$var wire 1 ( clk $end
$var wire 28 / data_in [27:0] $end
$var wire 1 * rst $end
$var wire 1 + start $end
$var wire 1 , we $end
$var parameter 4 0 ADD_1 $end
$var parameter 4 1 ADD_2 $end
$var parameter 4 2 ADD_BIAS $end
$var parameter 4 3 ASSIGN $end
$var parameter 4 4 FINISH $end
$var parameter 4 5 LOAD_DATA $end
$var parameter 4 6 MULTIPLY $end
$var parameter 4 7 RELU $end
$var parameter 32 8 WIDTH $end
$var parameter 32 9 n_b $end
$var parameter 32 : n_w $end
$var parameter 32 ; n_x $end
$var reg 28 < B [27:0] $end
$var reg 4 = STATE [3:0] $end
$var reg 28 > W1 [27:0] $end
$var reg 28 ? W2 [27:0] $end
$var reg 28 @ W3 [27:0] $end
$var reg 28 A W4 [27:0] $end
$var reg 28 B X1 [27:0] $end
$var reg 28 C X2 [27:0] $end
$var reg 28 D X3 [27:0] $end
$var reg 28 E X4 [27:0] $end
$var reg 28 F data_out [27:0] $end
$var reg 1 ! data_valid $end
$var reg 1 G done_loading $end
$var reg 5 H neuron_key [4:0] $end
$var reg 3 I output_key [2:0] $end
$var reg 28 J temp [27:0] $end
$var reg 28 K temp_add1 [27:0] $end
$var reg 28 L temp_add2 [27:0] $end
$var reg 3 M y_key [2:0] $end
$upscope $end
$upscope $end
$enddefinitions $end
$comment Show the parameter values. $end
$dumpall
b100 ;
b110110 :
b10011 9
b11100 8
b101 7
b11 6
b1 5
b110 4
b10 3
b100 2
b1000 1
b111 0
b100 &
b110110 %
b10011 $
b11100 #
$end
#0
$dumpvars
bx M
bx L
bx K
bx J
bx I
bx H
xG
bx F
bx E
bx D
bx C
bx B
bx A
bx @
bx ?
bx >
bx =
bx <
b0 /
b0 .
bx -
0,
0+
1*
b0 )
0(
b0 '
bx "
x!
$end
#5000
b1 =
0G
b0 <
b0 A
b0 @
b0 ?
b0 >
b0 E
b0 D
b0 C
b0 B
1(
#10000
0(
b0 -
1,
0*
#15000
b1 -
1(
#20000
0(
#25000
b1 )
b1 /
b1 '
b1 .
b10 -
1(
#30000
0(
#35000
b10 '
b10 .
b11 -
1(
#40000
0(
#45000
b0 )
b0 /
b11 '
b11 .
b0 -
1(
#50000
0(
#55000
b110 )
b110 /
b100 '
b100 .
b1 -
1(
#60000
0(
#65000
b1111111111111111111111111101 )
b1111111111111111111111111101 /
b101 '
b101 .
b10 -
1(
#70000
0(
#75000
b101 )
b101 /
b110 '
b110 .
b11 -
1(
#80000
0(
#85000
b1111111111111111111111110000 )
b1111111111111111111111110000 /
b111 '
b111 .
b100 -
1(
#90000
0(
#95000
b10101 )
b10101 /
b1000 '
b1000 .
b101 -
1(
#100000
0(
#105000
b10000 )
b10000 /
b1001 '
b1001 .
b110 -
1(
#110000
0(
#115000
b1111111111111111111111111010 )
b1111111111111111111111111010 /
b1010 '
b1010 .
b111 -
1(
#120000
0(
#125000
b1111111111111111111111110111 )
b1111111111111111111111110111 /
b1011 '
b1011 .
b1000 -
1(
#130000
0(
#135000
b11 )
b11 /
b1100 '
b1100 .
b1001 -
1(
#140000
0(
#145000
b1111111111111111111111111101 )
b1111111111111111111111111101 /
b1101 '
b1101 .
b1010 -
1(
#150000
0(
#155000
b1111111111111111111111110001 )
b1111111111111111111111110001 /
b1110 '
b1110 .
b1011 -
1(
#160000
0(
#165000
b1111111111111111111111101111 )
b1111111111111111111111101111 /
b1111 '
b1111 .
b1100 -
1(
#170000
0(
#175000
b10010 )
b10010 /
b10000 '
b10000 .
b1101 -
1(
#180000
0(
#185000
b1100 )
b1100 /
b10001 '
b10001 .
b1110 -
1(
#190000
0(
#195000
b1111111111111111111111111100 )
b1111111111111111111111111100 /
b10010 '
b10010 .
b1111 -
1(
#200000
0(
#205000
b1111111111111111111111111000 )
b1111111111111111111111111000 /
b10011 '
b10011 .
b10000 -
1(
#210000
0(
#215000
b100 )
b100 /
b10100 '
b10100 .
b10001 -
1(
#220000
0(
#225000
b1110 )
b1110 /
b10101 '
b10101 .
b10010 -
1(
#230000
0(
#235000
b1000 )
b1000 /
b10110 '
b10110 .
b10011 -
1(
#240000
0(
#245000
b1111 )
b1111 /
b10111 '
b10111 .
b10100 -
1(
#250000
0(
#255000
b1111111111111111111111110010 )
b1111111111111111111111110010 /
b11000 '
b11000 .
b10101 -
1(
#260000
0(
#265000
b1110 )
b1110 /
b11001 '
b11001 .
b10110 -
1(
#270000
0(
#275000
b1001 )
b1001 /
b11010 '
b11010 .
b10111 -
1(
#280000
0(
#285000
b1111 )
b1111 /
b11011 '
b11011 .
b11000 -
1(
#290000
0(
#295000
b1110 )
b1110 /
b11100 '
b11100 .
b11001 -
1(
#300000
0(
#305000
b110 )
b110 /
b11101 '
b11101 .
b11010 -
1(
#310000
0(
#315000
b111 )
b111 /
b11110 '
b11110 .
b11011 -
1(
#320000
0(
#325000
b1 )
b1 /
b11111 '
b11111 .
b11100 -
1(
#330000
0(
#335000
b1111111111111111111111111000 )
b1111111111111111111111111000 /
b100000 '
b100000 .
b11101 -
1(
#340000
0(
#345000
b1110 )
b1110 /
b100001 '
b100001 .
b11110 -
1(
#350000
0(
#355000
b100 )
b100 /
b100010 '
b100010 .
b11111 -
1(
#360000
0(
#365000
b1111111111111111111111110010 )
b1111111111111111111111110010 /
b100011 '
b100011 .
b100000 -
1(
#370000
0(
#375000
b1110 )
b1110 /
b100100 '
b100100 .
b100001 -
1(
#380000
0(
#385000
b100101 '
b100101 .
b100010 -
1(
#390000
0(
#395000
b1000 )
b1000 /
b100110 '
b100110 .
b100011 -
1(
#400000
0(
#405000
b1001 )
b1001 /
b100111 '
b100111 .
b100100 -
1(
#410000
0(
#415000
b1111 )
b1111 /
b101000 '
b101000 .
b100101 -
1(
#420000
0(
#425000
b101001 '
b101001 .
b100110 -
1(
#430000
0(
#435000
b1011 )
b1011 /
b101010 '
b101010 .
b100111 -
1(
#440000
0(
#445000
b1001 )
b1001 /
b101011 '
b101011 .
b101000 -
1(
#450000
0(
#455000
b1010 )
b1010 /
b101100 '
b101100 .
b101001 -
1(
#460000
0(
#465000
b1 )
b1 /
b101101 '
b101101 .
b101010 -
1(
#470000
0(
#475000
b1111111111111111111111111001 )
b1111111111111111111111111001 /
b101110 '
b101110 .
b101011 -
1(
#480000
0(
#485000
b1111111111111111111111111010 )
b1111111111111111111111111010 /
b101111 '
b101111 .
b101100 -
1(
#490000
0(
#495000
b1111111111111111111111110001 )
b1111111111111111111111110001 /
b110000 '
b110000 .
b101101 -
1(
#500000
0(
#505000
b10001 )
b10001 /
b110001 '
b110001 .
b101110 -
1(
#510000
0(
#515000
b1010 )
b1010 /
b110010 '
b110010 .
b101111 -
1(
#520000
0(
#525000
b1011 )
b1011 /
b110011 '
b110011 .
b110000 -
1(
#530000
0(
#535000
b1111111111111111111111111011 )
b1111111111111111111111111011 /
b110100 '
b110100 .
b110001 -
1(
#540000
0(
#545000
b100 )
b100 /
b110101 '
b110101 .
b110010 -
1(
#550000
0(
#555000
b1111111111111111111111111001 )
b1111111111111111111111111001 /
b110110 '
b110110 .
b110011 -
1(
#560000
0(
#565000
b110111 '
b110111 .
b110100 -
1(
#570000
0(
#575000
b111 )
b111 /
b111000 '
b111000 .
b110101 -
1(
#580000
0(
#585000
b1100 )
b1100 /
b111001 '
b111001 .
b0 -
1(
#590000
0(
#595000
b1 )
b1 /
b111010 '
b111010 .
b1 -
1(
#600000
0(
#605000
b0 )
b0 /
b111011 '
b111011 .
b10 -
1(
#610000
0(
#615000
b10 )
b10 /
b111100 '
b111100 .
b11 -
1(
#620000
0(
#625000
b1111111111111111111111111111 )
b1111111111111111111111111111 /
b111101 '
b111101 .
b100 -
1(
#630000
0(
#635000
b1 )
b1 /
b111110 '
b111110 .
b101 -
1(
#640000
0(
#645000
b100 )
b100 /
b111111 '
b111111 .
b110 -
1(
#650000
0(
#655000
b101 )
b101 /
b1000000 '
b1000000 .
b111 -
1(
#660000
0(
#665000
b1010 )
b1010 /
b1000001 '
b1000001 .
b1000 -
1(
#670000
0(
#675000
b1111111111111111111111111100 )
b1111111111111111111111111100 /
b1000010 '
b1000010 .
b1001 -
1(
#680000
0(
#685000
b10100 )
b10100 /
b1000011 '
b1000011 .
b1010 -
1(
#690000
0(
#695000
b0 )
b0 /
b1000100 '
b1000100 .
b1011 -
1(
#700000
0(
#705000
b101 )
b101 /
b1000101 '
b1000101 .
b1100 -
1(
#710000
0(
#715000
b11 )
b11 /
b1000110 '
b1000110 .
b1101 -
1(
#720000
0(
#725000
b1 )
b1 /
b1000111 '
b1000111 .
b1110 -
1(
#730000
0(
#735000
b10 )
b10 /
b1001000 '
b1001000 .
b1111 -
1(
#740000
0(
#745000
b1111111111111111111111110110 )
b1111111111111111111111110110 /
b1001001 '
b1001001 .
b10000 -
1(
#750000
0(
#755000
b1010 )
b1010 /
b1001010 '
b1001010 .
b10001 -
1(
#760000
0(
#765000
b1001011 '
b1001011 .
b10010 -
1(
#770000
0(
#775000
b1111111111111111111111110110 )
b1111111111111111111111110110 /
b1001100 '
b1001100 .
b10011 -
1(
#780000
0(
#785000
b0 H
1G
b10 =
1(
#790000
0(
#795000
b11 =
b1 H
b0 M
b1 <
b1111111111111111111111110000 A
b101 @
b1111111111111111111111111101 ?
b110 >
b1 D
b1 C
0,
1(
#800000
0(
#805000
b111 =
1(
#810000
0(
#815000
b1000 =
b101 L
b1111111111111111111111111101 K
1(
#820000
0(
#825000
b100 =
1(
#830000
0(
#835000
b101 =
1(
#840000
0(
#845000
b10 =
b11 J
1(
#850000
0(
#855000
b11 =
b10 H
b1 M
b0 <
b1111111111111111111111110111 A
b1111111111111111111111111010 @
b10000 ?
b10101 >
1(
#860000
0(
#865000
b111 =
1(
#870000
0(
#875000
b1000 =
b1111111111111111111111111010 L
b10000 K
1(
#880000
0(
#885000
b100 =
1(
#890000
0(
#895000
b101 =
1(
#900000
0(
#905000
b10 =
b1010 J
1(
#910000
0(
#915000
b11 =
b11 H
b10 M
b10 <
b1111111111111111111111101111 A
b1111111111111111111111110001 @
b1111111111111111111111111101 ?
b11 >
1(
#920000
0(
#925000
b111 =
1(
#930000
0(
#935000
b1000 =
b1111111111111111111111110001 L
b1111111111111111111111111101 K
1(
#940000
0(
#945000
b100 =
1(
#950000
0(
#955000
b101 =
1(
#960000
0(
#965000
b10 =
b1111111111111111111111110000 J
1(
#970000
0(
#975000
b100 H
b11 =
b11 M
b1111111111111111111111111111 <
b1111111111111111111111111000 A
b1111111111111111111111111100 @
b1100 ?
b10010 >
1(
#980000
0(
#985000
b111 =
1(
#990000
0(
#995000
b1000 =
b1111111111111111111111111100 L
b1100 K
1(
#1000000
0(
#1005000
b100 =
1(
#1010000
0(
#1015000
b101 =
1(
#1020000
0(
#1025000
b10 =
b111 J
1(
#1030000
0(
#1035000
b11 =
b101 H
b0 M
b1 <
b1111 A
b1000 @
b1110 ?
b100 >
b111 E
b0 D
b1010 C
b11 B
1(
#1040000
0(
#1045000
b111 =
1(
#1050000
0(
#1055000
b1000 =
b1101001 L
b10011000 K
1(
#1060000
0(
#1065000
b100 =
1(
#1070000
0(
#1075000
b101 =
1(
#1080000
0(
#1085000
b10 =
b100000010 J
1(
#1090000
0(
#1095000
b11 =
b110 H
b1 M
b100 <
b1001 @
b1111111111111111111111110010 >
1(
#1100000
0(
#1105000
b111 =
1(
#1110000
0(
#1115000
b1000 =
b1100010 K
1(
#1120000
0(
#1125000
b100 =
1(
#1130000
0(
#1135000
b101 =
1(
#1140000
0(
#1145000
b10 =
b11001111 J
1(
#1150000
0(
#1155000
b11 =
b111 H
b0 M
b101 <
b0 A
b0 @
b110 ?
b1110 >
b0 E
b11001111 C
b100000010 B
1(
#1160000
0(
#1165000
b111 =
1(
#1170000
0(
#1175000
b1000 =
b0 L
b1001011110110 K
1(
#1180000
0(
#1185000
b100 =
1(
#1190000
0(
#1195000
b101 =
1(
#1200000
0(
#1205000
b10 =
b1001011111011 J
1(
#1210000
0(
#1215000
b11 =
b1000 H
b1010 <
b0 ?
b111 >
b0 C
b1001011111011 B
1(
#1220000
0(
#1225000
b111 =
1(
#1230000
0(
#1235000
b1000 =
b1000010011011101 K
1(
#1240000
0(
#1245000
b100 =
1(
#1250000
0(
#1255000
b101 =
1(
#1260000
0(
#1265000
b10 =
b1000010011100111 J
1(
#1270000
0(
#1275000
b11 =
b1001 H
b1111111111111111111111111100 <
b1 >
b1000010011100111 B
1(
#1280000
0(
#1285000
b111 =
1(
#1290000
0(
#1295000
b1000 =
b1000010011100111 K
1(
#1300000
0(
#1305000
b100 =
1(
#1310000
0(
#1315000
b101 =
1(
#1320000
0(
#1325000
b10 =
b1000010011100011 J
1(
#1330000
0(
#1335000
b11 =
b1010 H
b10100 <
b1111111111111111111111111000 >
b1000010011100011 B
1(
#1340000
0(
#1345000
b111 =
1(
#1350000
0(
#1355000
b1000 =
b1111111110111101100011101000 K
1(
#1360000
0(
#1365000
b100 =
1(
#1370000
0(
#1375000
b101 =
1(
#1380000
0(
#1385000
b10 =
b1111111110111101100011111100 J
1(
#1390000
0(
#1395000
b11 =
b1011 H
b1 M
b0 <
b1110 >
1(
#1400000
0(
#1405000
b111 =
1(
#1410000
0(
#1415000
b1000 =
b1110100010001101010 K
1(
#1420000
0(
#1425000
b100 =
1(
#1430000
0(
#1435000
b101 =
1(
#1440000
0(
#1445000
b10 =
b1110100010001101010 J
1(
#1450000
0(
#1455000
b11 =
b1100 H
b0 M
b101 <
b1111111111111111111111110010 ?
b100 >
b1110100010001101010 C
b0 B
1(
#1460000
0(
#1465000
b111 =
1(
#1470000
0(
#1475000
b1000 =
b1111100110100100001000110100 K
1(
#1480000
0(
#1485000
b100 =
1(
#1490000
0(
#1495000
b101 =
1(
#1500000
0(
#1505000
b10 =
b1111100110100100001000111001 J
1(
#1510000
0(
#1515000
b11 =
b1101 H
b1 M
b11 <
b1110 ?
b1110 >
1(
#1520000
0(
#1525000
b111 =
1(
#1530000
0(
#1535000
b1000 =
b11001011011110111001100 K
1(
#1540000
0(
#1545000
b100 =
1(
#1550000
0(
#1555000
b101 =
1(
#1560000
0(
#1565000
b10 =
b11001011011110111001111 J
1(
#1570000
0(
#1575000
b11 =
b1110 H
b10 M
b1 <
b1001 ?
b1000 >
1(
#1580000
0(
#1585000
b111 =
1(
#1590000
0(
#1595000
b1000 =
b10000010110011110111010 K
1(
#1600000
0(
#1605000
b100 =
1(
#1610000
0(
#1615000
b101 =
1(
#1620000
0(
#1625000
b10 =
b10000010110011110111011 J
1(
#1630000
0(
#1635000
b11 =
b1111 H
b11 M
b10 <
b1111 ?
b1111 >
1(
#1640000
0(
#1645000
b111 =
1(
#1650000
0(
#1655000
b1000 =
b11011010000001000110110 K
1(
#1660000
0(
#1665000
b100 =
1(
#1670000
0(
#1675000
b101 =
1(
#1680000
0(
#1685000
b10 =
b11011010000001000111000 J
1(
#1690000
0(
